py_txi/__init__.py
py_txi/inference_server.py
py_txi/text_embedding_inference.py
py_txi/text_generation_inference.py
py_txi/utils.py
py_txi-0.10.0.dist-info/LICENSE
py_txi-0.10.0.dist-info/METADATA
py_txi-0.10.0.dist-info/WHEEL
py_txi-0.10.0.dist-info/top_level.txt
py_txi-0.10.0.dist-info/RECORD
