Metadata-Version: 2.1
Name: py-txi
Version: 0.10.0
Summary: A Python wrapper around TGI and TEI servers
Home-page: https://github.com/IlyasMoutawwakil/py-txi
Author: Ilyas Moutawwakil
Author-email: ilyas.moutawwakil@gmail.com
Keywords: tgi,llm,tei,embedding,huggingface,docker,python
Platform: linux
Platform: windows
Platform: macos
Classifier: Programming Language :: Python :: 3
Classifier: Natural Language :: English
License-File: LICENSE
Requires-Dist: docker
Requires-Dist: huggingface-hub
Requires-Dist: numpy
Requires-Dist: aiohttp
Provides-Extra: quality
Requires-Dist: ruff; extra == "quality"
Provides-Extra: testing
Requires-Dist: pytest; extra == "testing"
